{
	"apiMethods": [
		{
			"host": "https://oms.fortunet.ch/backend/",
			"name": "login",
			"method": "/login"
		},
		{
			"host": "https://oms.fortunet.ch/backend/",
			"name": "addorder",
			"method": "/order"
		},
		{
			"host": "https://oms.fortunet.ch/backend/",
			"name": "orders",
			"method": "/orders"
		},
		{
			"host": "https://oms.fortunet.ch/backend/",
			"name": "deleteorder",
			"method": "/order"
		},
		{
			"host": "https://oms.fortunet.ch/backend/",
			"name": "updateorder",
			"method": "/order"
		}
	]
}
